asyncio_throttle/__init__.py
asyncio_throttle/py.typed
asyncio_throttle/throttler.py
asyncio_throttle-1.0.2.dist-info/LICENSE
asyncio_throttle-1.0.2.dist-info/METADATA
asyncio_throttle-1.0.2.dist-info/WHEEL
asyncio_throttle-1.0.2.dist-info/top_level.txt
asyncio_throttle-1.0.2.dist-info/RECORD
